crispy_forms_propeller/__init__.py
crispy_forms_propeller/forms.py
crispy_forms_propeller/layout/__init__.py
crispy_forms_propeller/layout/base.py
crispy_forms_propeller/locale/de/LC_MESSAGES/django.po
crispy_forms_propeller/locale/fr/LC_MESSAGES/django.po
crispy_forms_propeller/models.py
crispy_forms_propeller/settings.py
crispy_forms_propeller/static/js/crispy_forms_foundation/plugins.js
crispy_forms_propeller/templates/propeller/accordion-group.html
crispy_forms_propeller/templates/propeller/accordion.html
crispy_forms_propeller/templates/propeller/betterform.html
crispy_forms_propeller/templates/propeller/display_form.html
crispy_forms_propeller/templates/propeller/errors.html
crispy_forms_propeller/templates/propeller/errors_formset.html
crispy_forms_propeller/templates/propeller/field.html
crispy_forms_propeller/templates/propeller/inputs.html
crispy_forms_propeller/templates/propeller/layout/alert.html
crispy_forms_propeller/templates/propeller/layout/baseinput.html
crispy_forms_propeller/templates/propeller/layout/button.html
crispy_forms_propeller/templates/propeller/layout/buttonholder.html
crispy_forms_propeller/templates/propeller/layout/checkboxselectmultiple.html
crispy_forms_propeller/templates/propeller/layout/checkboxselectmultiple_inline.html
crispy_forms_propeller/templates/propeller/layout/div.html
crispy_forms_propeller/templates/propeller/layout/field_errors.html
crispy_forms_propeller/templates/propeller/layout/field_errors_block.html
crispy_forms_propeller/templates/propeller/layout/field_with_buttons.html
crispy_forms_propeller/templates/propeller/layout/fieldset.html
crispy_forms_propeller/templates/propeller/layout/formactions.html
crispy_forms_propeller/templates/propeller/layout/help_text.html
crispy_forms_propeller/templates/propeller/layout/help_text_and_errors.html
crispy_forms_propeller/templates/propeller/layout/inline_field.html
crispy_forms_propeller/templates/propeller/layout/multifield.html
crispy_forms_propeller-0.0.2a13.dist-info/LICENSE
crispy_forms_propeller-0.0.2a13.dist-info/WHEEL
crispy_forms_propeller-0.0.2a13.dist-info/METADATA
crispy_forms_propeller-0.0.2a13.dist-info/RECORD
